openevsehttp/__init__.py
openevsehttp/__main__.py
openevsehttp/const.py
openevsehttp/exceptions.py
openevsehttp/websocket.py
python_openevse_http-0.2.3.dist-info/licenses/LICENSE
python_openevse_http-0.2.3.dist-info/METADATA
python_openevse_http-0.2.3.dist-info/WHEEL
python_openevse_http-0.2.3.dist-info/top_level.txt
python_openevse_http-0.2.3.dist-info/RECORD
